LICENSE
MANIFEST.in
README.md
setup.cfg
setup.py
psalpsdtools/Edrw.py
psalpsdtools/PhRegPrv.py
psalpsdtools/__init__.py
psalpsdtools/convert xlsx to xlsm.py
psalpsdtools/edit links.py
psalpsdtools/superscript.py
psalpsdtools/usage.py
psalpsdtools.egg-info/PKG-INFO
psalpsdtools.egg-info/SOURCES.txt
psalpsdtools.egg-info/dependency_links.txt
psalpsdtools.egg-info/not-zip-safe
psalpsdtools.egg-info/requires.txt
psalpsdtools.egg-info/top_level.txt