Metadata-Version: 2.1
Name: psalpsdtools
Version: 1.5
Summary: PSA-LPSD Tools
Home-page: https://github.com/tondiaz/psalpsdtools
Author-email: a.diaziii@psa.gov.ph
License: MIT
License-File: LICENSE
